sca/__init__.py
sca/funclib.py
sca/graph.py
sca/rlocus.py
sca_fiuna-0.2.1.1.dist-info/LICENSE
sca_fiuna-0.2.1.1.dist-info/METADATA
sca_fiuna-0.2.1.1.dist-info/WHEEL
sca_fiuna-0.2.1.1.dist-info/top_level.txt
sca_fiuna-0.2.1.1.dist-info/RECORD
